{
  "name": "Adjust Aura apply speed",
  "description": "Adjusts the time it takes for the auras to apply",
  "author": "Jeo",
  "website": "https://github.com/naghi32/D2RMODS/tree/main/AdjustAuraSpeed",
  "version": "1.0",
  "config": [
    {
      "id": "perdelay",
      "type": "number",
      "name": "Aura delay",
      "description": "Set aura delay between 1 and 99.",
      "defaultValue": 50,
      "minValue": 1,
      "maxValue": 99
    },
	 {
      "id": "damagefix",
      "type": "checkbox",
      "name": "Damage fix",
      "description": "Enable to fix aura damage",
      "defaultValue": true
    },
    {
      "id": "basedmgfix",
      "type": "number",
      "name": "Damage Fix ",
      "description": "Calculate aura damage from a base aura delay between 1 and 250.",
      "defaultValue": 50,
      "minValue": 1,
      "maxValue": 250
    }
  ]
}
